{
  "$schema": "http://json-schema.org/draft-07/schema#",
  "$id": "timesheetEntry",
  "title": "TimesheetEntry",
  "type": "object",
  "properties": {
    "date": {
      "type": "string",
      "format": "date"
    },
    "worked": {
      "type": "number"
    },
    "internal_hours": {
      "type": "number"
    },
    "courses": {
      "type": "number"
    },
    "leave": {
      "type": "number"
    },
    "special_leave": {
      "type": "number"
    },
    "part_time_leave": {
      "type": "number"
    },
    "sick": {
      "type": "number"
    },
    "doctor": {
      "type": "number"
    },
    "standby": {
      "type": "number"
    }
  }
}